package_locator/__init__.py
package_locator/__main__.py
package_locator/common.py
package_locator/directory.py
package_locator/locator.py
package_locator/py.typed
package_locator-0.4.4.dist-info/entry_points.txt
package_locator-0.4.4.dist-info/LICENSE
package_locator-0.4.4.dist-info/WHEEL
package_locator-0.4.4.dist-info/METADATA
package_locator-0.4.4.dist-info/RECORD
