Metadata-Version: 2.1
Name: package-locator
Version: 0.4.4
Summary: For a package, locate its source repository url and its relative path within the repository
Home-page: https://github.com/nasifimtiazohi/package-locator
License: MIT
Author: Nasif Imtiaz
Author-email: nasifimtiaz88@gmail.com
Requires-Python: >=3.7.1,<4.0.0
Classifier: License :: OSI Approved :: MIT License
Classifier: Programming Language :: Python :: 3
Classifier: Programming Language :: Python :: 3.10
Classifier: Programming Language :: Python :: 3.6
Classifier: Programming Language :: Python :: 3.7
Classifier: Programming Language :: Python :: 3.8
Classifier: Programming Language :: Python :: 3.9
Requires-Dist: GitPython (>=3.1.24,<4.0.0)
Requires-Dist: PyYAML (>=5.4.1,<6.0.0)
Requires-Dist: click (>=8.0.0,<9.0.0)
Requires-Dist: requests (>=2.26.0,<3.0.0)
Requires-Dist: rich (>=10.3.0,<11.0.0)
Requires-Dist: toml (>=0.10.2,<0.11.0)
Requires-Dist: version-differ (>=0.3.14,<0.4.0)
Project-URL: Documentation, https://package-locator.readthedocs.io
Project-URL: Repository, https://github.com/nasifimtiazohi/package-locator
